testpackageforjoblibsigma/__init__.py
testpackageforjoblibsigma/__main__.py
testpackageforjoblibsigma/cli.py
testpackageforjoblibsigma/for_sigma.py
testpackageforjoblibsigma/joblib_sigma.py
testpackageforjoblibsigma/play.py
testpackageforjoblibsigma-0.1.9.dist-info/LICENSE
testpackageforjoblibsigma-0.1.9.dist-info/WHEEL
testpackageforjoblibsigma-0.1.9.dist-info/entry_points.txt
testpackageforjoblibsigma-0.1.9.dist-info/METADATA
testpackageforjoblibsigma-0.1.9.dist-info/RECORD
