Metadata-Version: 2.1
Name: testpackageforjoblibsigma
Version: 0.1.9
Summary: test to make package and set up python environment
Home-page: https://github.com/tk-tanab/testpackage
License: Apache-2.0
Author: tk-tanab
Author-email: tk-tanab@ist.osaka-u.ac.jp
Requires-Python: >=3.10,<4.0
Classifier: License :: OSI Approved :: Apache Software License
Classifier: Programming Language :: Python :: 3
Classifier: Programming Language :: Python :: 3.10
Classifier: Programming Language :: Python :: 3.11
Requires-Dist: joblib (>=1.2.0,<2.0.0)
Project-URL: Repository, https://github.com/tk-tanab/testpackage
